examples/alu_seq/HDLSrc/alu.sv
module alu (
    input  wire        clk,  
    input  wire        reset,
    input  wire [31:0] a,     
    input  wire [31:0] b,     
    input  wire [3:0]  alu_op,
    output reg  [31:0] result,
    output             zero   
);

    // Definición de operaciones
    localparam [3:0] 
        ALU_ADD = 4'b0000, // Suma
        ALU_SUB = 4'b0001, // Resta
        ALU_AND = 4'b0010, // AND lógico
        ALU_OR  = 4'b0011, // OR lógico
        ALU_XOR = 4'b0100, // XOR lógico
        ALU_SLL = 4'b0101, // Shift left logical
        ALU_SRL = 4'b0110, // Shift right logical
        ALU_SRA = 4'b0111, // Shift right arithmetic
        ALU_SLT = 4'b1000; // Menor que (signed)

    // Indicador de si el resultado es cero
    assign zero = (result == 32'b0) ? 1'b1 : 1'b0;

    // Bloque secuencial
    always @(posedge clk or posedge reset) begin
        if (reset) begin
            result <= 32'b0;
        end else begin
            // Operaciones de la ALU
            case (alu_op)
                ALU_ADD: result <= a + b;
                ALU_SUB: result <= a - b;
                ALU_AND: result <= a & b;
                ALU_OR:  result <= a | b;
                ALU_XOR: result <= a ^ b;
                // Usar los 5 bits menos significativos de B
                ALU_SLL: result <= a << b[4:0]; 
                ALU_SRL: result <= a >> b[4:0];
                ALU_SRA: result <= $signed(a) >>> b[4:0];
                ALU_SLT: result <= ($signed(a) < $signed(b)) ? 32'b1 : 32'b0;
                default: result <= 32'b0; // Operación no válida
            endcase
        end
    end
endmodule

examples/fromDocument/alu_simple_seq/OSimon/dut_signals.vcd
$date
	Wed Feb 26 18:42:24 2025
$end
$version
	Icarus Verilog
$end
$timescale
	1ps
$end
$scope module alu $end
$var wire 32 ! a [31:0] $end
$var wire 4 " alu_op [3:0] $end
$var wire 32 # b [31:0] $end
$var wire 1 $ clk $end
$var wire 1 % reset $end
$var wire 1 & zero $end
$var parameter 4 ' ALU_ADD $end
$var parameter 4 ( ALU_AND $end
$var parameter 4 ) ALU_OR $end
$var parameter 4 * ALU_SLL $end
$var parameter 4 + ALU_SLT $end
$var parameter 4 , ALU_SRA $end
$var parameter 4 - ALU_SRL $end
$var parameter 4 . ALU_SUB $end
$var parameter 4 / ALU_XOR $end
$var reg 32 0 result [31:0] $end
$upscope $end
$enddefinitions $end
$comment Show the parameter values. $end
$dumpall
b100 /
b1 .
b110 -
b111 ,
b1000 +
b101 *
b11 )
b10 (
b0 '
$end
#0
$dumpvars
b0 0
1&
0%
1$
b1010 #
b111 "
b100 !
$end
#500
0$
#1000
b1101 #
b10 !
b1111 "
1$
#1500
0$
#2000
b1010 #
b1011 !
1$
#2500
0$
#3000
b1111 #
b10000 !
b1010 "
1$
#3500
0$
#4000
b1010 #
b100 !
b1000 "
1$
#4500
0$
#5000
b10100 #
b1111 !
b110 "
0&
b1 0
1$
#5500
0$
#6000
b1111 #
b10010 !
b11 "
1&
b0 0
1$
#6500
0$
#7000
b1000 #
b1001 !
b0 "
0&
b11111 0
1$
#7500
0$
#8000
b1010 #
b10001 !
b111 "
b10001 0
1$
#8500
0$
#9000
b10011 #
b110 !
b1010 "
1&
b0 0
1$
