examples/MyFsm/HDLSrc/MyFSM.v
///////////////////////////////////////////////////////////////////////////////////////////////////
//
// Example Finite State Machine
// Copyright @ 2023
// This is the Module for My Finite State Machine
//
///////////////////////////////////////////////////////////////////////////////////////////////////

module MyFSM(

        input i_clk,
		input i_rst_n,

        input i_x,

        output  reg o_y,
		
		output [1:0] o_state);

    reg [1:0] state;


    always @ (posedge i_clk or negedge i_rst_n)
	
	if (!i_rst_n) begin
	    state <= 2'b00;
		o_y <= 1'b0;
    end
    else
      begin
        case (state)

            2'b00: state <= i_x?2'b01:2'b00;

            2'b01: state <= i_x?2'b10:2'b00;

            2'b10: state <= i_x?2'b11:2'b00;

            2'b11: state <= 2'b00;
        endcase
        o_y <= state[1] & state[0] & i_x;
      end 

	assign o_state = state;
endmodule

examples/MyFsm/OSimon/dut_signals.vcd
$date
	Thu Jul 16 23:56:00 2026
$end
$version
	Icarus Verilog
$end
$timescale
	1ps
$end
$scope module MyFSM $end
$var wire 1 ! i_clk $end
$var wire 1 " i_rst_n $end
$var wire 1 # i_x $end
$var wire 2 $ o_state [1:0] $end
$var reg 1 % o_y $end
$var reg 2 & state [1:0] $end
$upscope $end
$enddefinitions $end
$comment Show the parameter values. $end
$dumpall
$end
#0
$dumpvars
b0 &
0%
b0 $
0#
1"
1!
$end
#500
0!
#1000
1!
#1500
0!
#2000
1#
1!
#2500
0!
#3000
0#
b1 $
b1 &
1!
#3500
0!
#4000
b0 $
b0 &
1!
#4500
0!
#5000
1!
#5500
0!
#6000
1#
1!
#6500
0!
#7000
0#
b1 $
b1 &
1!
#7500
0!
#8000
b0 $
b0 &
1!
#8500
0!
#9000
1!
#9500
0!
#10000
1!
#10500
0!
#11000
1!
#11500
0!
#12000
1#
1!
#12500
0!
#13000
0#
b1 $
b1 &
1!
#13500
0!
#14000
b0 $
b0 &
1!
#14500
0!
#15000
1#
1!
#15500
0!
#16000
b1 $
b1 &
1!
#16500
0!
#17000
0#
b10 $
b10 &
1!
#17500
0!
#18000
b0 $
b0 &
1!
#18500
0!
#19000
1#
1!
#19500
0!
#20000
b1 $
b1 &
1!
#20500
0!
#21000
0#
b10 $
b10 &
1!
#21500
0!
#22000
b0 $
b0 &
1!
#22500
0!
#23000
1#
1!
#23500
0!
#24000
b1 $
b1 &
1!
#24500
0!
#25000
0#
b10 $
b10 &
1!
#25500
0!
#26000
b0 $
b0 &
1!
#26500
0!
#27000
1#
1!
#27500
0!
#28000
0#
b1 $
b1 &
1!
#28500
0!
#29000
1#
b0 $
b0 &
1!
#29500
0!
#30000
b1 $
b1 &
1!
#30500
0!
#31000
0#
b10 $
b10 &
1!
#31500
0!
#32000
1#
b0 $
b0 &
1!
#32500
0!
#33000
b1 $
b1 &
1!
#33500
0!
#34000
0#
b10 $
b10 &
1!
#34500
0!
#35000
b0 $
b0 &
1!
#35500
0!
#36000
1#
1!
#36500
0!
#37000
b1 $
b1 &
1!
#37500
0!
#38000
0#
b10 $
b10 &
1!
#38500
0!
#39000
1#
b0 $
b0 &
1!
#39500
0!
#40000
b1 $
b1 &
1!
#40500
0!
#41000
b10 $
b10 &
1!
#41500
0!
#42000
b11 $
b11 &
1!
#42500
0!
#43000
0#
1%
b0 $
b0 &
1!
#43500
0!
#44000
1#
0%
1!
#44500
0!
#45000
0#
b1 $
b1 &
1!
#45500
0!
#46000
1#
b0 $
b0 &
1!
#46500
0!
#47000
b1 $
b1 &
1!
#47500
0!
#48000
0#
b10 $
b10 &
1!
#48500
0!
#49000
b0 $
b0 &
1!
#49500
0!
#50000
1!
#50500
0!
#51000
1#
1!
#51500
0!
#52000
b1 $
b1 &
1!
#52500
0!
#53000
b10 $
b10 &
1!
#53500
0!
#54000
0#
b11 $
b11 &
1!
#54500
0!
#55000
1#
b0 $
b0 &
1!
#55500
0!
#56000
b1 $
b1 &
1!
#56500
0!
#57000
0#
b10 $
b10 &
1!
#57500
0!
#58000
1#
b0 $
b0 &
1!
#58500
0!
#59000
b1 $
b1 &
1!
#59500
0!
#60000
b10 $
b10 &
1!
#60500
0!
#61000
b11 $
b11 &
1!
#61500
0!
#62000
1%
b0 $
b0 &
1!
#62500
0!
#63000
0#
0%
b1 $
b1 &
1!
#63500
0!
#64000
b0 $
b0 &
1!
