examples/alu_moniciclo_uvm/HDLSrc/Sumador.v
//**********************************************************************************************//
//  TITLE:                  Adder 32 bits					                                          //
//                                                                                              //
//  PROJECT:                Monociclo                                                           //
//                                                                                              //
//  LANGUAGE:               Verilog						                                             //
//                                                                                              //
//  AUTHOR:                 Lagarto Development Team - lagarto@cic.ipn.mx						      //
//                                                                                              //
//  REVISION:               1.0 - Monociclo CORE2021                                            //
//                                                                                              //
//**********************************************************************************************//
 
module Sumador #(
	parameter				WORD = 32		//ancho de operadores
  )(
 	input		[WORD-1:0]	opea,		//operador a
	input		[WORD-1:0]	opeb,		//operador b
	input						cin,		//acarreo de entrada
	output	[WORD-1:0]	sal,		//resultado
	output					cout		//acarreo de salida
 
 );
	//señal intermedia para acarreos
	wire		[WORD-1:0]	carry;
	
	//instanciar sumador N bits
	genvar i;
	generate
		for (i = 0; i < WORD; i = i + 1)
		begin	:sumadorNbits
			if (i == 0)
				Sumador_2bits sum	(opea[i], opeb[i], cin, sal[i], carry[i]);
			else
				Sumador_2bits sum	(opea[i], opeb[i], carry[i-1], sal[i], carry[i]);
		end
	endgenerate
	
	assign	cout = carry[WORD-1];
	
 endmodule 

 
 module	Sumador_2bits (
	input				opea,		//operador a
	input				opeb,		//operador b
	input				cin,		//acarreo de entrada
	output			sal,		//resultado
	output			cout		//acarreo de salida
 );
	 //calculo de resultado
	 assign	sal	= opea + opeb + cin;
	 
	 //calculo de acarreo de salida
	 assign	cout	= (opea*opeb) + ((opea+opeb) * cin);
 
 endmodule 
 
 
// module Sumador (
// 	input		[3:0]	opea,		//operador a
//	input		[3:0]	opeb,		//operador b
//	input				cin,		//acarreo de entrada
//	output	[3:0]	sal,		//resultado
//	output			cout		//acarreo de salida
// 
// );
//	//señal intermedia para acarreos
//	wire		[2:0]	carry;
//	
//	//instanciar sumadores 2 bits
//	Sumador_2bits suma (opea[0], opeb[0], cin, sal[0], carry[0]);			//sumador a
//	Sumador_2bits sumb (opea[1], opeb[1], carry[0], sal[1], carry[1]);	//sumador b
//	Sumador_2bits sumc (opea[2], opeb[2], carry[1], sal[2], carry[2]);	//sumador c
//	Sumador_2bits sumd (opea[3], opeb[3], carry[2], sal[3], cout);			//sumador d
//		
// endmodule

examples/AluMonocicloUvm/HDLSrc/ALU.sv
//**********************************************************************************************//
//  TITLE:                  ALU - EXECUTION                                                     //
//                                                                                              //
//  PROJECT:                Monociclo                                                           //
//                                                                                              //
//  LANGUAGE:               Verilog                                                             //
//                                                                                              //
//  AUTHOR:                 Lagarto Development Team - lagarto@cic.ipn.mx                       //
//                                                                                              //
//  REVISION:               1.0 - Monociclo CORE2021                                            //
//                                                                                              //
//**********************************************************************************************//
module	ALU #(
	parameter			WORD	= 32,
	parameter			ALUOP	= 4
)(
	input			[WORD-1:0]	ex_datars1_i,
	input			[WORD-1:0]	ex_datars2_i,
	input			[ALUOP-1:0]	ex_aluop_i,
	output reg	[WORD-1:0]	ex_data_o,
	output						ex_zerof_o
);

	//wire 			bne_o;
	assign		ex_zerof_o = (ex_data_o == 32'h0) ? 1'b1 : 1'b0;	//BEQ
					
//	assign		ex_difeq_o = |(ex_data_o);
//	initial
//	begin
//		bne_o = 1'b0;
//	end
	
	wire			[WORD-1:0]	add_result_o;
	wire							add_cout_o;
	
	always @(*)
	begin

		case (ex_aluop_i)
			4'h8:		ex_data_o = add_result_o;
			4'h1:		ex_data_o = ex_datars1_i - ex_datars2_i;
			4'h2:		ex_data_o = ex_datars1_i * ex_datars2_i;
			4'h3:		ex_data_o = ex_datars1_i / ex_datars2_i;
			4'h4:		ex_data_o = ex_datars1_i & ex_datars2_i;
			4'h5:		ex_data_o = ex_datars1_i ^ ex_datars2_i;
			4'h6:		ex_data_o = ex_datars1_i | ex_datars2_i;
			4'h7:		ex_data_o = ex_datars1_i << 2;
			4'hD:		ex_data_o = ex_datars1_i >>> ex_datars2_i; //sra
			4'hE:		ex_data_o = ex_datars1_i >> ex_datars2_i; //sla
			4'h9:		ex_data_o = (ex_datars1_i < ex_datars2_i); //slt
			4'hA:		ex_data_o = (ex_datars1_i < ex_datars2_i); //sltu PENDIENTE
			
	
			default:	ex_data_o = 32'b0;
		
		
		endcase
	
	end
	
	Sumador	Adder_U1 (
		.opea			(ex_datars1_i),	//operador a
		.opeb			(ex_datars2_i),	//operador b
		.cin			(1'b0),				//acarreo de entrada
		.sal			(add_result_o),	//resultado
		.cout			(add_cout_o)		//acarreo de salida
	);
	
endmodule

examples/alu_moniciclo_uvm/OSimon/dut_signals.vcd
$date
	Sun Jan  5 20:29:40 2025
$end
$version
	Icarus Verilog
$end
$timescale
	1ps
$end
$scope module ALU $end
$var wire 4 ! ex_aluop_i [3:0] $end
$var wire 32 " ex_datars1_i [31:0] $end
$var wire 32 # ex_datars2_i [31:0] $end
$var wire 1 $ ex_zerof_o $end
$var wire 32 % add_result_o [31:0] $end
$var wire 1 & add_cout_o $end
$var parameter 32 ' ALUOP $end
$var parameter 32 ( WORD $end
$var reg 32 ) ex_data_o [31:0] $end
$upscope $end
$enddefinitions $end
$comment Show the parameter values. $end
$dumpall
b100000 (
b100 '
$end
#0
$dumpvars
b0 )
0&
b101110 %
1$
b11111 #
b1111 "
b1110 !
$end
#1000
b10011110 %
0$
b11111111111111111111111111110100 )
b1010101 #
b1001001 "
b1 !
#2000
b10010110 %
1$
b0 )
b1001100 #
b1001010 "
b1110 !
#3000
b1111100 %
0$
b1 )
b1011111 #
b11101 "
b1001 !
#4000
b111110 %
b1110110001 )
b11011 #
b100011 "
b10 !
#5000
b101001 %
b100111 )
b111 #
b100010 "
b110 !
#6000
b1001010 %
b1101000 )
b110000 #
b11010 "
b111 !
#7000
b1000011 %
b1000011 )
b100011 #
b100000 "
b1000 !
#8000
b1010 %
b1 )
b1000 #
b10 "
b1001 !
#9000
b1101011 %
1$
b0 )
b1000111 #
b100100 "
b1101 !
