examples/alu_moniciclo_uvm/HDLSrc/Sumador.v
//**********************************************************************************************//
//  TITLE:                  Adder 32 bits					                                          //
//                                                                                              //
//  PROJECT:                Monociclo                                                           //
//                                                                                              //
//  LANGUAGE:               Verilog						                                             //
//                                                                                              //
//  AUTHOR:                 Lagarto Development Team - lagarto@cic.ipn.mx						      //
//                                                                                              //
//  REVISION:               1.0 - Monociclo CORE2021                                            //
//                                                                                              //
//**********************************************************************************************//
 
module Sumador #(
	parameter				WORD = 32		//ancho de operadores
  )(
 	input		[WORD-1:0]	opea,		//operador a
	input		[WORD-1:0]	opeb,		//operador b
	input						cin,		//acarreo de entrada
	output	[WORD-1:0]	sal,		//resultado
	output					cout		//acarreo de salida
 
 );
	//señal intermedia para acarreos
	wire		[WORD-1:0]	carry;
	
	//instanciar sumador N bits
	genvar i;
	generate
		for (i = 0; i < WORD; i = i + 1)
		begin	:sumadorNbits
			if (i == 0)
				Sumador_2bits sum	(opea[i], opeb[i], cin, sal[i], carry[i]);
			else
				Sumador_2bits sum	(opea[i], opeb[i], carry[i-1], sal[i], carry[i]);
		end
	endgenerate
	
	assign	cout = carry[WORD-1];
	
 endmodule 

 
 module	Sumador_2bits (
	input				opea,		//operador a
	input				opeb,		//operador b
	input				cin,		//acarreo de entrada
	output			sal,		//resultado
	output			cout		//acarreo de salida
 );
	 //calculo de resultado
	 assign	sal	= opea + opeb + cin;
	 
	 //calculo de acarreo de salida
	 assign	cout	= (opea*opeb) + ((opea+opeb) * cin);
 
 endmodule 
 
 
// module Sumador (
// 	input		[3:0]	opea,		//operador a
//	input		[3:0]	opeb,		//operador b
//	input				cin,		//acarreo de entrada
//	output	[3:0]	sal,		//resultado
//	output			cout		//acarreo de salida
// 
// );
//	//señal intermedia para acarreos
//	wire		[2:0]	carry;
//	
//	//instanciar sumadores 2 bits
//	Sumador_2bits suma (opea[0], opeb[0], cin, sal[0], carry[0]);			//sumador a
//	Sumador_2bits sumb (opea[1], opeb[1], carry[0], sal[1], carry[1]);	//sumador b
//	Sumador_2bits sumc (opea[2], opeb[2], carry[1], sal[2], carry[2]);	//sumador c
//	Sumador_2bits sumd (opea[3], opeb[3], carry[2], sal[3], cout);			//sumador d
//		
// endmodule

examples/AluMonocicloUvm/HDLSrc/ALU.sv
//**********************************************************************************************//
//  TITLE:                  ALU - EXECUTION                                                     //
//                                                                                              //
//  PROJECT:                Monociclo                                                           //
//                                                                                              //
//  LANGUAGE:               Verilog                                                             //
//                                                                                              //
//  AUTHOR:                 Lagarto Development Team - lagarto@cic.ipn.mx                       //
//                                                                                              //
//  REVISION:               1.0 - Monociclo CORE2021                                            //
//                                                                                              //
//**********************************************************************************************//
module	ALU #(
	parameter			WORD	= 32,
	parameter			ALUOP	= 4
)(
	input			[WORD-1:0]	ex_datars1_i,
	input			[WORD-1:0]	ex_datars2_i,
	input			[ALUOP-1:0]	ex_aluop_i,
	output reg	[WORD-1:0]	ex_data_o,
	output						ex_zerof_o
);

	//wire 			bne_o;
	assign		ex_zerof_o = (ex_data_o == 32'h0) ? 1'b1 : 1'b0;	//BEQ
					
//	assign		ex_difeq_o = |(ex_data_o);
//	initial
//	begin
//		bne_o = 1'b0;
//	end
	
	wire			[WORD-1:0]	add_result_o;
	wire							add_cout_o;
	
	always @(*)
	begin

		case (ex_aluop_i)
			4'h8:		ex_data_o = add_result_o;
			4'h1:		ex_data_o = ex_datars1_i - ex_datars2_i;
			4'h2:		ex_data_o = ex_datars1_i * ex_datars2_i;
			4'h3:		ex_data_o = ex_datars1_i / ex_datars2_i;
			4'h4:		ex_data_o = ex_datars1_i & ex_datars2_i;
			4'h5:		ex_data_o = ex_datars1_i ^ ex_datars2_i;
			4'h6:		ex_data_o = ex_datars1_i | ex_datars2_i;
			4'h7:		ex_data_o = ex_datars1_i << 2;
			4'hD:		ex_data_o = ex_datars1_i >>> ex_datars2_i; //sra
			4'hE:		ex_data_o = ex_datars1_i >> ex_datars2_i; //sla
			4'h9:		ex_data_o = (ex_datars1_i < ex_datars2_i); //slt
			4'hA:		ex_data_o = (ex_datars1_i < ex_datars2_i); //sltu PENDIENTE
			
	
			default:	ex_data_o = 32'b0;
		
		
		endcase
	
	end
	
	Sumador	Adder_U1 (
		.opea			(ex_datars1_i),	//operador a
		.opeb			(ex_datars2_i),	//operador b
		.cin			(1'b0),				//acarreo de entrada
		.sal			(add_result_o),	//resultado
		.cout			(add_cout_o)		//acarreo de salida
	);
	
endmodule

examples/AluMonocicloUvm/OSimon/dut_signals.vcd
$date
	Thu Jul 16 11:48:26 2026
$end
$version
	Icarus Verilog
$end
$timescale
	1ps
$end
$scope module ALU $end
$var wire 4 ! ex_aluop_i [3:0] $end
$var wire 32 " ex_datars1_i [31:0] $end
$var wire 32 # ex_datars2_i [31:0] $end
$var wire 1 $ ex_zerof_o $end
$var wire 32 % add_result_o [31:0] $end
$var wire 1 & add_cout_o $end
$var parameter 32 ' ALUOP $end
$var parameter 32 ( WORD $end
$var reg 32 ) ex_data_o [31:0] $end
$upscope $end
$enddefinitions $end
$comment Show the parameter values. $end
$dumpall
b100000 (
b100 '
$end
#0
$dumpvars
b0 )
0&
b10111010 %
1$
b111 #
b10110011 "
b1111 !
$end
#1000
b100100110 %
b1111010 #
b10101100 "
b1001 !
#2000
b11110111 %
b10111001 #
b111110 "
b11 !
#3000
b10110000 %
0$
b110001 )
b110101 #
b1111011 "
b100 !
#4000
b11010101 %
b11010101 )
b1010011 #
b10000010 "
b1000 !
#5000
b100011010 %
b100110010101001 )
b1111101 #
b10011101 "
b10 !
#6000
b100100110 %
1$
b0 )
b10010011 #
b10010011 "
b1 !
#7000
b1111000 %
0$
b1 )
b1001110 #
b101010 "
b1001 !
#8000
b10011110 %
1$
b0 )
b11100 #
b10000010 "
b1110 !
#9000
b100110111 %
0$
b10000000 )
b10000001 #
b10110110 "
b100 !
#10000
b11110110 %
b1 )
b10111000 #
b111110 "
b1010 !
#11000
b10101001 %
1$
b0 )
b10101 #
b10010100 "
b1100 !
#12000
b11101110 %
b10010100 #
b1011010 "
b11 !
#13000
b11110110 %
b10100111 #
b1001111 "
b1111 !
#14000
b10011111 %
0$
b10011111 )
b10011001 #
b110 "
b101 !
#15000
b100101111 %
1$
b0 )
b10011100 #
b10010011 "
b1110 !
#16000
b10111110 %
0$
b1011110 )
b1 #
b10111101 "
b1101 !
#17000
b1011000 %
b1010100 )
b1010010 #
b110 "
b101 !
#18000
b10010010 %
b100011 )
b100111 #
b1101011 "
b100 !
#19000
b11001110 %
b1010000 )
b1011100 #
b1110010 "
#20000
b10100010 %
b10100010 )
b1011010 #
b1001000 "
b1000 !
#21000
b10010000 %
b10100 )
b1011100 #
b110100 "
b100 !
#22000
b100100110 %
1$
b0 )
b10000001 #
b10100101 "
b1110 !
#23000
b10110000 %
0$
b10110000 )
b111011 #
b1110101 "
b1000 !
#24000
b10100101 %
b1000001 )
b110010 #
b1110011 "
b101 !
#25000
b10000011 %
1$
b0 )
b10000011 #
b0 "
b10 !
#26000
b10111110 %
0$
b11111111111111111111111110101100 )
b10001001 #
b110101 "
b1 !
#27000
b1101101 %
b10000 )
b10000 #
b1011101 "
b100 !
#28000
b10001011 %
b1110111 )
b1010111 #
b110100 "
b110 !
#29000
b11011110 %
b1 )
b10000101 #
b1011001 "
b1010 !
#30000
b11100101 %
1$
b0 )
b10110110 #
b101111 "
b11 !
#31000
b10011111 %
b101011 #
b1110100 "
b1011 !
#32000
b1111010 %
0$
b1111010 )
b1010 #
b1110000 "
b1000 !
#33000
b10011000 %
b1100100 )
b11110 #
b1111010 "
b101 !
#34000
b101001011 %
1$
b0 )
b10110111 #
b10010100 "
b11 !
#35000
b100011 %
0$
b11000100 )
b111 #
b11100 "
b10 !
#36000
b100010 %
1$
b0 )
b11111 #
b11 "
b1101 !
#37000
b11010100 %
b10101011 #
b101001 "
#38000
b10101010 %
0$
b1011010 )
b1011000 #
b1010010 "
b110 !
#39000
b11000110 %
1$
b0 )
b10000101 #
b1000001 "
b1101 !
#40000
b11101100 %
0$
b10010000 )
b101110 #
b10111110 "
b101 !
#41000
b1101100 %
b1100100000 )
b1100100 #
b1000 "
b10 !
#42000
b1011011 %
b100011 )
b111111 #
b11100 "
b101 !
#43000
b11101000 %
b11101000 )
b1000011 #
b10100101 "
b1000 !
#44000
b11110100 %
b100 )
b1111100 #
b1111000 "
b101 !
#45000
b10111010 %
b1000011000 )
b110100 #
b10000110 "
b111 !
#46000
b100110010 %
b1 )
b11001000 #
b1101010 "
b1001 !
#47000
b11110111 %
b11000100 #
b110011 "
#48000
b10001101 %
b1001000111000 )
b1011000 #
b110101 "
b10 !
#49000
b11011 %
b11 )
b1100 #
b1111 "
b1 !
