examples/fifo_generica/HDLSrc/fifo_gen.sv
//*************************************************************	
// Proyecto: 				MEM  FIFO WPXRP 
// Archivo: 				fifo_generic.v
// Organización: 			Instituto Politécnico Nacional
// Autor: 					Lagarto team
// E-mail: 					Lagarto@cic.ipn.mx
// Referencias: 			Libro Lagarto I, Capítulo 4
//*************************************************************

module fifo_gen #(parameter 
							  DBi = 64		  , 
							  DBo = 64		  , 
							  ABi = 64		  , 
							  ABo = 64		  ,
							  CBi =  8		  , 
							  CBo =  8		  ,  								
								 E = 16		   						 
)    (
 input              		clk_i         ,  
 input              		rst_ni        , 
 input              		rd_i          , // señal de habilitacion de lectura
 input              		wr_i          , // señal de hablitacion de escritura
 input       [DBi-1:00] data_i        , // bus de datos       de entrada
 input       [ABi-1:00] address_i     , // bus de direcciones de entrada
 input       [CBi-1:00] command_i     , // bus de comandos    de entrada 
 output      [DBo-1:00]	data_o        , // bus de datos       de salida 
 output      [ABo-1:00]	address_o     , // bus de direcciones de salida
 output      [CBo-1:00]	command_o     , // bus de comandos    de salida
 output reg          	den			  , // bus de comandos    de salida
 output      		 		empty         , // señal de fifo vacia
 output      				full            // señal de fifo totalmente llena

);

localparam P = $clog2(E)              ;
reg	            [P-1:0] entries     ; 
wire [(CBi+DBi+ABi)-1:00] data_wr     ;
reg                       rd_reg      ;

// Memoria FIFO de E entradas x RB bits
reg [(CBi+DBi+ABi)-1:00] fifo [E-1:0] ;  // FIFO MEM 
// 
assign data_wr = {{command_i},{address_i},{data_i}};   

reg          [P-1:00] tail     ;        
reg          [P-1:00] head     ;        
reg 			 [P-1:00] index_reg;
 		
 assign full  = (tail == E-1 ) & (entries == E); // llena 
 assign empty = (head == tail) & (entries == 0); // vacia
 
// Escritura por ciclo 
always @(posedge clk_i)   
begin	
   if (wr_i) begin
	    fifo [tail] <= data_wr; // 	 
	end
end

// Lectura por ciclo 
always @(posedge clk_i, negedge rst_ni)   
begin
   if (rst_ni == 0) begin
	    rd_reg    <= 1'b0;
	    index_reg <= {P{1'b0}};
	end
	else if (rd_i) begin
	    rd_reg    <= rd_i;
	    index_reg <= head;	 
	end
	else begin
	rd_reg    <= 1'b0;
	end
end


// Etapa de salida 
assign {{command_o},{address_o},{data_o}} = (rd_reg)? fifo[index_reg]:{(CBi+ABi+DBi){1'b0}}; 
 



always @(posedge clk_i, negedge rst_ni)
begin
  if (rst_ni == 0) begin				   	   // inicializa registros
		 head  <= {P{1'b0}};
		 tail  <= {P{1'b0}}; 
        den  <= 1'b0;	
	 entries  <= {P{1'b0}};;	
  end
  else  begin 
	  case ({rd_i,wr_i}) 							// lecturas y escrituras	 
	        2'b00: begin 
			         tail     <= tail;
						head     <= head;
						den      <= 1'b0;						
			  end			  
	   	  2'b01: begin  // Escritura        // caso: rdwr=01 -se trata de escritura				  
				  if (!full ) begin         		// si no esta totalmente llena!
						 tail    <= (tail + 3'h1);	// escribe 1 entrada
						 entries <=  entries + 1'b1;
						 den     <=  1'b0;
				  end
	   	  end // 2'd1 	     
	   	  2'b10: begin  // Lectura          // caso: fb_rdwr=10 -se trata de lectura	   	  	  
	   	  	  if (!empty) begin              // si no esta vacia
	   	  	       head    <= (head + 3'h1);	// 
						  den    <=  1'b1;
					 entries    <=  entries - 1'b1;
	   	  	  end
	   	  end // 2'd2 
	   	  2'b11: begin                      // caso: fb_rdwr=11 -se trata de lectura-Escritura	   	  	  
	   	  	  if (!empty) begin              // si no esta vacia
				       tail    <= (tail + 3'h1);	// escribe 1 entrada
	   	  	       head    <= (head + 3'h1);	// 
						  den    <=  1'b1;
	   	  	  end
	   	  end // 2'd2 
	   	  default: begin            			// caso:default
			  			head   <= head;
						den    <= 1'b0;	
	   	  end // 2'd2 				   		
	   endcase // fb_rdwr
	end
end

endmodule

examples/fifo_generica/OSimon/dut_signals.vcd
$date
	Tue Jan  7 01:10:08 2025
$end
$version
	Icarus Verilog
$end
$timescale
	1ps
$end
$scope module fifo_gen $end
$var wire 64 ! address_i [63:0] $end
$var wire 1 " clk_i $end
$var wire 8 # command_i [7:0] $end
$var wire 64 $ data_i [63:0] $end
$var wire 1 % empty $end
$var wire 1 & full $end
$var wire 1 ' rd_i $end
$var wire 1 ( rst_ni $end
$var wire 1 ) wr_i $end
$var wire 136 * data_wr [135:0] $end
$var wire 64 + data_o [63:0] $end
$var wire 8 , command_o [7:0] $end
$var wire 64 - address_o [63:0] $end
$var parameter 32 . ABi $end
$var parameter 32 / ABo $end
$var parameter 32 0 CBi $end
$var parameter 32 1 CBo $end
$var parameter 32 2 DBi $end
$var parameter 32 3 DBo $end
$var parameter 32 4 E $end
$var parameter 32 5 P $end
$var reg 1 6 den $end
$var reg 4 7 entries [3:0] $end
$var reg 4 8 head [3:0] $end
$var reg 4 9 index_reg [3:0] $end
$var reg 1 : rd_reg $end
$var reg 4 ; tail [3:0] $end
$upscope $end
$enddefinitions $end
$comment Show the parameter values. $end
$dumpall
b100 5
b10000 4
b1000000 3
b1000000 2
b1000 1
b1000 0
b1000000 /
b1000000 .
$end
#0
$dumpvars
b0 ;
0:
b0 9
b0 8
b0 7
06
b0 -
b0 ,
b0 +
b1110001100000000000000000000000000000000000000000000000000000000001001110000000000000000000000000000000000000000000000000000000100110111 *
1)
1(
0'
0&
1%
b100110111 $
b11100011 #
1"
b100111 !
$end
#500
0"
#1000
b1010100000000000000000000000000000000000000000000000000000000000010000000000000000000000000000000000000000000000000000000000101111011 *
b1000 !
b101111011 $
b10101 #
0%
b1 7
b1 ;
1"
#1500
0"
#2000
b1111111100000000000000000000000000000000000000000000000000000000000100100000000000000000000000000000000000000000000000000000000011101111 *
b10010 !
b11101111 $
b11111111 #
b10 7
b10 ;
1"
#2500
0"
#3000
b1001010100000000000000000000000000000000000000000000000000000000010011110000000000000000000000000000000000000000000000000000000111011101 *
b1001111 !
b111011101 $
b10010101 #
b11 7
b11 ;
1"
#3500
0"
#4000
b111000000000000000000000000000000000000000000000000000000000010010010000000000000000000000000000000000000000000000000000000110001100 *
b1001001 !
b110001100 $
b1110 #
0)
1'
b100 7
b100 ;
1"
#4500
0"
#5000
b1011110100000000000000000000000000000000000000000000000000000000010011110000000000000000000000000000000000000000000000000000000001001100 *
b1001111 !
b1001100 $
b10111101 #
b100110111 +
b100111 -
b11100011 ,
b11 7
16
b1 8
1:
1"
#5500
0"
#6000
b1000100000000000000000000000000000000000000000000000000000000010101110000000000000000000000000000000000000000000000000000000000001110 *
b1010111 !
b1110 $
b10001 #
b101111011 +
b1000 -
b10101 ,
b1 9
b10 7
b10 8
1"
#6500
0"
#7000
b11101111 +
b10010 -
b11111111 ,
b1 7
b11 8
b10 9
1"
#7500
0"
#8000
b111011101 +
b1001111 -
b10010101 ,
1%
b11 9
b0 7
b100 8
1"
