examples/alu_seq/HDLSrc/alu.sv
module alu (
    input  wire        clk,  
    input  wire        reset,
    input  wire [31:0] a,     
    input  wire [31:0] b,     
    input  wire [3:0]  alu_op,
    output reg  [31:0] result,
    output             zero   
);

    // Definición de operaciones
    localparam [3:0] 
        ALU_ADD = 4'b0000, // Suma
        ALU_SUB = 4'b0001, // Resta
        ALU_AND = 4'b0010, // AND lógico
        ALU_OR  = 4'b0011, // OR lógico
        ALU_XOR = 4'b0100, // XOR lógico
        ALU_SLL = 4'b0101, // Shift left logical
        ALU_SRL = 4'b0110, // Shift right logical
        ALU_SRA = 4'b0111, // Shift right arithmetic
        ALU_SLT = 4'b1000; // Menor que (signed)

    // Indicador de si el resultado es cero
    assign zero = (result == 32'b0) ? 1'b1 : 1'b0;

    // Bloque secuencial
    always @(posedge clk or posedge reset) begin
        if (reset) begin
            result <= 32'b0;
        end else begin
            // Operaciones de la ALU
            case (alu_op)
                ALU_ADD: result <= a + b;
                ALU_SUB: result <= a - b;
                ALU_AND: result <= a & b;
                ALU_OR:  result <= a | b;
                ALU_XOR: result <= a ^ b;
                // Usar los 5 bits menos significativos de B
                ALU_SLL: result <= a << b[4:0]; 
                ALU_SRL: result <= a >> b[4:0];
                ALU_SRA: result <= $signed(a) >>> b[4:0];
                ALU_SLT: result <= ($signed(a) < $signed(b)) ? 32'b1 : 32'b0;
                default: result <= 32'b0; // Operación no válida
            endcase
        end
    end
endmodule

examples/AluSeq/OSimon/dut_signals.vcd
$date
	Thu Jul 16 11:55:39 2026
$end
$version
	Icarus Verilog
$end
$timescale
	1ps
$end
$scope module alu $end
$var wire 32 ! a [31:0] $end
$var wire 4 " alu_op [3:0] $end
$var wire 32 # b [31:0] $end
$var wire 1 $ clk $end
$var wire 1 % reset $end
$var wire 1 & zero $end
$var parameter 4 ' ALU_ADD $end
$var parameter 4 ( ALU_AND $end
$var parameter 4 ) ALU_OR $end
$var parameter 4 * ALU_SLL $end
$var parameter 4 + ALU_SLT $end
$var parameter 4 , ALU_SRA $end
$var parameter 4 - ALU_SRL $end
$var parameter 4 . ALU_SUB $end
$var parameter 4 / ALU_XOR $end
$var reg 32 0 result [31:0] $end
$upscope $end
$enddefinitions $end
$comment Show the parameter values. $end
$dumpall
b100 /
b1 .
b110 -
b111 ,
b1000 +
b101 *
b11 )
b10 (
b0 '
$end
#0
$dumpvars
b0 0
1&
0%
1$
b10110100 #
b100 "
b1110100 !
$end
#500
0$
#1000
b1001011 #
b111010 !
b1000 "
0&
b11000000 0
1$
#1500
0$
#2000
b1100011 #
b1100010 !
b11 "
b1 0
1$
#2500
0$
#3000
b10110100 #
b100101 !
b1100011 0
1$
#3500
0$
#4000
b1111110 #
b10100010 !
b101 "
b10110101 0
1$
#4500
0$
#5000
b111111 #
b10001101 !
b10 "
b10000000000000000000000000000000 0
1$
#5500
0$
#6000
b11000101 #
b1110011 !
b111 "
b1101 0
1$
#6500
0$
#7000
b10000101 #
b10000000 !
b0 "
b11 0
1$
#7500
0$
#8000
b1101 #
b1000100 !
b100 "
b100000101 0
1$
#8500
0$
#9000
b10101001 #
b1001 !
b1001001 0
1$
#9500
0$
#10000
b0 #
b1111111 !
b0 "
b10100000 0
1$
#10500
0$
#11000
b10011010 #
b10001100 !
b110 "
b1111111 0
1$
#11500
0$
#12000
b1001010 #
b11110 !
b1000 "
1&
b0 0
1$
#12500
0$
#13000
b11111 #
b1000111 !
b101 "
0&
b1 0
1$
#13500
0$
#14000
b110110 #
b1010101 !
b0 "
b10000000000000000000000000000000 0
1$
#14500
0$
#15000
b10001 #
b111010 !
b1000 "
b10001011 0
1$
#15500
0$
#16000
b111101 #
b10111101 !
b1 "
1&
b0 0
1$
#16500
0$
#17000
b10101000 #
b110101 !
b101 "
0&
b10000000 0
1$
#17500
0$
#18000
b1011110 #
b1001011 !
b1000 "
b11010100000000 0
1$
#18500
0$
#19000
b10000111 #
b100001 !
b11 "
b1 0
1$
#19500
0$
#20000
b1100101 #
b111001 !
b10100111 0
1$
#20500
0$
#21000
b110101 #
b1 !
b0 "
b1111101 0
1$
#21500
0$
#22000
b1011010 #
b111011 !
b110110 0
1$
#22500
0$
#23000
b11100 #
b110111 !
b110 "
b10010101 0
1$
#23500
0$
#24000
b100100 #
b101 !
b0 "
1&
b0 0
1$
#24500
0$
#25000
b1000010 #
b1101011 !
b11 "
0&
b101001 0
1$
#25500
0$
#26000
b1111111 #
b10011001 !
b100 "
b1101011 0
1$
#26500
0$
#27000
b10 #
b100001 !
b1 "
b11100110 0
1$
#27500
0$
#28000
b10010100 #
b10101010 !
b11111 0
1$
#28500
0$
#29000
b1010000 #
b110111 !
b10 "
b10110 0
1$
#29500
0$
#30000
b1000010 #
b110100 !
b0 "
b10000 0
1$
#30500
0$
#31000
b101011 #
b11000010 !
b110 "
b1110110 0
1$
#31500
0$
#32000
b10010011 #
b1010010 !
1&
b0 0
1$
#32500
0$
#33000
b10100111 #
b10100111 !
b11 "
1$
#33500
0$
#34000
b10011110 #
b1101010 !
0&
b10100111 0
1$
#34500
0$
#35000
b10000 #
b10101100 !
b110 "
b11111110 0
1$
#35500
0$
#36000
b10110011 #
b1100111 !
b10 "
1&
b0 0
1$
#36500
0$
#37000
b1011011 #
b1110010 !
b110 "
0&
b100011 0
1$
#37500
0$
#38000
b1011111 #
b10110 !
b1000 "
1&
b0 0
1$
#38500
0$
#39000
b1001000 #
b101 !
b110 "
0&
b1 0
1$
#39500
0$
#40000
b10111010 #
b111 !
b10 "
1&
b0 0
1$
#40500
0$
#41000
b100011 #
b100110 !
b1000 "
0&
b10 0
1$
#41500
0$
#42000
b1101010 #
b10110101 !
1&
b0 0
1$
#42500
0$
#43000
b1 #
b10011111 !
b110 "
1$
#43500
0$
#44000
b11000000 #
b101 !
b1 "
0&
b1001111 0
1$
#44500
0$
#45000
b10110101 #
b10000101 !
b100 "
b11111111111111111111111101000101 0
1$
#45500
0$
#46000
b111100 #
b10111010 !
b1 "
b110000 0
1$
#46500
0$
#47000
b1101011 #
b1111010 !
b1111110 0
1$
#47500
0$
#48000
b10000011 #
b11011 !
b0 "
b1111 0
1$
#48500
0$
#49000
b11001000 #
b10010 !
b111 "
b10011110 0
1$
#49500
0$
#50000
1&
b0 0
1$
