examples/AluComb/HDLSrc/alu.sv
module alu (
    input  wire [31:0] a, 
    input  wire [31:0] b, 
    input  wire [3:0]  alu_op,
    output reg  [31:0] result, 
    output             zero 
);

    // Definición de operaciones
    localparam [3:0] 
        ALU_ADD = 4'b0000, // Suma
        ALU_SUB = 4'b0001, // Resta
        ALU_AND = 4'b0010, // AND lógico
        ALU_OR  = 4'b0011, // OR lógico
        ALU_XOR = 4'b0100, // XOR lógico
        ALU_SLL = 4'b0101, // Shift left logical
        ALU_SRL = 4'b0110, // Shift right logical
        ALU_SRA = 4'b0111, // Shift right arithmetic
        ALU_SLT = 4'b1000; // Menor que (signed)

    // Indicador de si el resultado es cero
    assign zero = (result == 32'b0) ? 1'b1 : 1'b0;

    always @(*) begin
        case (alu_op)
            ALU_ADD: result = a + b;
            ALU_SUB: result = a - b;
            ALU_AND: result = a & b;
            ALU_OR:  result = a | b;
            ALU_XOR: result = a ^ b;
            // Usar los 5 bits menos significativos de B
            ALU_SLL: result = a << b[4:0]; 
            ALU_SRL: result = a >> b[4:0];
            ALU_SRA: result = $signed(a) >>> b[4:0];
            ALU_SLT: result = ($signed(a) < $signed(b)) ? 32'b1 : 32'b0;
            default: result = 32'b0;
        endcase
    end
endmodule

examples/AluComb/OSimon/dut_signals.vcd
$date
	Thu Jul 16 11:26:05 2026
$end
$version
	Icarus Verilog
$end
$timescale
	1ps
$end
$scope module alu $end
$var wire 32 ! a [31:0] $end
$var wire 4 " alu_op [3:0] $end
$var wire 32 # b [31:0] $end
$var wire 1 $ zero $end
$var parameter 4 % ALU_ADD $end
$var parameter 4 & ALU_AND $end
$var parameter 4 ' ALU_OR $end
$var parameter 4 ( ALU_SLL $end
$var parameter 4 ) ALU_SLT $end
$var parameter 4 * ALU_SRA $end
$var parameter 4 + ALU_SRL $end
$var parameter 4 , ALU_SUB $end
$var parameter 4 - ALU_XOR $end
$var reg 32 . result [31:0] $end
$upscope $end
$enddefinitions $end
$comment Show the parameter values. $end
$dumpall
b100 -
b1 ,
b110 +
b111 *
b1000 )
b101 (
b11 '
b10 &
b0 %
$end
#0
$dumpvars
b0 .
1$
b1110010 #
b1000 "
b10000001 !
$end
#1000
0$
b1100001 .
b1000101 #
b10100110 !
b1 "
#2000
b111001 .
b111101 #
b111001 !
b10 "
#3000
1$
b0 .
b10000 #
b10101000 !
#4000
0$
b1111111 .
b1101100 #
b111011 !
b11 "
#5000
b110000000000000000000000000 .
b11000 #
b110 !
b101 "
#6000
b11 .
b10110001 #
b10110100 !
b1 "
#7000
b10101000 .
b10111001 #
b10101100 !
b10 "
#8000
b10 .
b10000010 #
b111 !
#9000
b100001 .
b1110010 #
b10010011 !
b1 "
#10000
b11011100 .
b1100011 #
b10111111 !
b100 "
#11000
b1010011 .
b1100111 #
b10111010 !
b1 "
#12000
b11011101 .
b10011001 #
b1000100 !
b100 "
#13000
b11111111111111111111111111101100 .
b11100 #
b1000 !
b1 "
#14000
b10000010 .
b10000 #
b1110010 !
b0 "
#15000
b10111111 .
b10110101 #
b101110 !
b11 "
#16000
b10000000000000000000000000000000 .
b1111111 #
b1101111 !
b101 "
#17000
b10010000 .
b1001 #
b10011001 !
b1 "
#18000
b111101 .
b10001001 #
b11000110 !
#19000
b10110001 .
b10110101 #
b100 !
b100 "
#20000
b10110111 .
b10010111 !
b11 "
#21000
b100000000000000000000000000000 .
b111101 #
b100001 !
b101 "
#22000
b1111110 .
b1000110 #
b1111000 !
b11 "
#23000
b1110100000000000000000000000000 .
b1111010 #
b1011101 !
b101 "
#24000
b1110011 .
b1010000 #
b1100011 !
b11 "
#25000
b1111110 .
b1 #
b1111111 !
b1 "
#26000
b100010011 .
b10011101 #
b1110110 !
b0 "
#27000
b11111111111111111111111111111111 .
b1110001 #
b1110000 !
b1 "
#28000
b1100101 .
b100111 #
b10001100 !
#29000
b10000010 .
b10100110 #
b10010010 !
b10 "
#30000
b10110000000000000000000000000000 .
b10011011 #
b1110110 !
b101 "
#31000
b10100101 .
b111010 #
b1101011 !
b0 "
#32000
1$
b0 .
b1110011 #
b1001001 !
b111 "
#33000
0$
b10 .
b1110010 #
b10000110 !
b10 "
#34000
1$
b0 .
b10001 #
b10111100 !
b110 "
#35000
0$
b1011000 .
b1000111 #
b11111 !
b100 "
#36000
b11111111 .
b11000101 #
b111010 !
b0 "
#37000
b10011110 .
b10011000 #
b11110 !
b11 "
#38000
b1110111 .
b110100 #
b1010011 !
#39000
b1 .
b10111010 #
b10100011 !
b1000 "
#40000
b11101100000000000000000000000000 .
b111010 #
b111011 !
b101 "
#41000
b11100111 .
b1101111 #
b1111000 !
b0 "
#42000
b1 .
b11000010 #
b100100 !
b1000 "
#43000
1$
b0 .
b111000 #
b1111000 !
#44000
0$
b10000 .
b11111 #
b10010000 !
b10 "
#45000
1$
b0 .
b101111 #
b11001 !
b110 "
#46000
b10011111 #
b10111100 !
b1000 "
#47000
b101001 #
b1001 !
b110 "
#48000
b101011 #
b1101101 !
b111 "
#49000
0$
b1 .
b1111000 #
b111 !
b1000 "
